Workbook
Name Cab_Det_1: 分类1!$A$44
Name Cab_Det_1: 分类1!$A$44
Name Cab_Subsum_1: 分类1!$A$64
Name Cab_Subsum_1: 分类1!$A$66
Name Cab_Sum_1: 分类1!$A$7
Name Cab_Sum_1: 分类1!$A$7
Name Cab_Tolsum_1: 分类1!$A$71
Name Cab_Tolsum_1: 分类1!$A$71

Sheet 领料清单
A1: [公司名称]
A2: 成套设备装配领料单
A3: 工程名称 ： [项目名称]
A4: 队组名称 ： *** | F4: 制表日期：
A5: 序号 | B5: 名称 | C5: 型 号 | D5: 单位 | E5: 数量 | F5: 生产厂家 | G5: 领料人 | I5: 领料人 | K5: 备注
G6: 数量 | H6: 签字 | I6: 数量 | J6: 签字
B7: [元器件名称] | C7: [元器件型号] | D7: [单位] | E7: [数量] | K7: [库存标记]
B11: 合计
A13: 编制人： 编制复核人： 发货人： 发货复核人： 装配队组负责人：

Sheet 项目信息
A1: =T(B22) -> 扬州华科
A2: =T(B23)
A4: 工程信息
A5: 项目名称 | E5: 项目编号
A6: 描述 | E6: 报价交期
A7: 报价单号
A8: 报价人 | B8: 李四
A9: 创建日期
A10: 报价审核人
A11: 项目负责人
A12: 项目备注
A13: 客户信息
A14: 客户名称
A15: 联系人
A16: 联系电话
A17: 客户地址
A18: 客户邮编
A19: 客户网址
A20: 客户email
A21: 本企业信息
A22: 单位名称 | B22: 扬州华科
A23: 英文名称
A24: 联系人
A25: 联系电话
A26: 销售地区
A27: 分类汇总 金额单位：人民币元
A28: 序号 | B28: 分类名称 | C28: 箱柜数量 | D28: 总 价 | E28: 成本 | F28: 毛利 | G28: 毛利率 | H28: 分类属性
A29: =ROW()-ROW(A$28) -> 1 | B29: =MID(CELL("filename",分类1!$A$1),FIND("]",CELL("filename",分类1!$A$1))+1,31) -> 分类1 | C29: =IF(H29="箱变",分类1!F35,分类1!F31*IF(分类1!F35="",1,分类1!F35)) -> 1 | D29: =ROUND(分类1!H35,2) -> 0 | E29: =ROUND(分类1!J35,2) -> 0 | F29: =ROUND((D29-E29),2) -> 0 | G29: =IF(D29=0,0,F29/D29) -> 0 | H29: =IF(OR(ISNUMBER(FIND("箱变", B29))=TRUE,ISNUMBER(FIND("欧变", B29))=TRUE,ISNUMBER(FIND("美变", B29))=TRUE,ISNUMBER(FIND("KVA", UPPER(B29)))=TRUE,ISNUMBER(FIND("箱式变电", B29))=TRUE),"箱变","常规") -> 常规
A30: =ROW()-ROW(A$28) -> 2
A31: =ROW()-ROW(A$28) -> 3
A32: =ROW()-ROW(A$28) -> 4
A33: =ROW()-ROW(A$28) -> 5
A34: =ROW()-ROW(A$28) -> 6
A35: =ROW()-ROW(A$28) -> 7
A36: =ROW()-ROW(A$28) -> 8
A37: =ROW()-ROW(A$28) -> 9
A38: =ROW()-ROW(A$28) -> 10
A39: =ROW()-ROW(A$28) -> 11
A40: =ROW()-ROW(A$28) -> 12
A41: =ROW()-ROW(A$28) -> 13
... A52: =ROW()-ROW(A$28) -> 24
A53: =ROW()-ROW(A$28) -> 25 | B53: 小计 | C53: =ROUND(SUM(C28:INDEX(C:C,ROW()-1)),2) -> 1 | D53: =ROUND(SUM(D28:INDEX(D:D,ROW()-1)),2) -> 0 | E53: =ROUND(SUM(E28:INDEX(E:E,ROW()-1)),2) -> 0 | F53: =SUM(F28:INDEX(F:F,ROW()-1)) -> 0 | G53: =IF(D53=0,0,F53/D53) -> 0 | H53: =SUM(H28:INDEX(H:H,ROW()-1)) -> 0
A54: =ROW()-ROW(A$28) -> 26 | B54: 运费 | D54: 0
A55: =ROW()-ROW(A$28) -> 27 | B55: 合计 | D55: =ROUND(SUM(D53:D54),2) -> 0
A56: =ROW()-ROW(A$28) -> 28 | B56: 人民币大写 | C56: =TEXT(SUBSTITUTE(IF(D55="","",IF(MOD(D55,1)=0,TEXT(INT(D55),"[DBNum2][$-804]G/通用格式元整"),(TEXT(INT(D55),"[DBNum2][$-804]G/通用格式元")&TEXT((INT(D55*10)-INT(D55)*10),"[DBNum2][$-804]G/通用格式角")&TEXT((INT(D55*100)-INT(D55*10)*10),"[DBNum2][$-804]G/通用格式分")))),"零角","零"),) -> 零元整
A57: 报表说明

Sheet 分类1
A2: =T(INDIRECT("项目信息!B22")) -> 扬州华科
A3: =T(INDIRECT("项目信息!B23"))
A4: 成套产品报价清单 金额单位：人民币元
A5: {=CONCATENATE("项目名称:",INDIRECT("项目信息!$B$5"))} -> 项目名称: | H5: =CONCATENATE("报价序号:", INDIRECT("'项目信息'!B7")) -> 报价序号:
A6: 序号 | B6: 柜号 | C6: 箱柜名称 | D6: 箱柜型号 | E6: 单位 | F6: 数量 | G6: 单 价 | H6: 总 价 | I6: 备注 | J6: 成本总价 | K6: 毛利 | L6: 毛利率 | M6: 箱柜尺寸 | N6: 类别 | O6: 预留 | P6: 预留 | Q6: 图号
A7: =ROW()-ROW(A$6) -> 1 | B7: 箱柜1 | E7: 台 | F7: 1 | G7: =G71 -> 0 | H7: =F7*G7 -> 0 | J7: =K71 -> 0 | K7: =H7-J7 -> 0 | L7: =IF(H7=0,0,K7/H7) -> 0
A8: =ROW()-ROW(A$6) -> 2
A9: =ROW()-ROW(A$6) -> 3
A10: =ROW()-ROW(A$6) -> 4
A11: =ROW()-ROW(A$6) -> 5
A12: =ROW()-ROW(A$6) -> 6
A13: =ROW()-ROW(A$6) -> 7
A14: =ROW()-ROW(A$6) -> 8
A15: =ROW()-ROW(A$6) -> 9
A16: =ROW()-ROW(A$6) -> 10
A17: =ROW()-ROW(A$6) -> 11
A18: =ROW()-ROW(A$6) -> 12
A19: =ROW()-ROW(A$6) -> 13
... A30: =ROW()-ROW(A$6) -> 24
A31: =ROW()-ROW(A$6) -> 25 | B31: 小计 | E31: 台 | F31: =SUM(F6:INDEX(F:F,ROW()-1)) -> 1 | H31: =ROUND(SUM(H6:INDEX(H:H,ROW()-1)),2) -> 0 | J31: =ROUND(SUM(J6:INDEX(J:J,ROW()-1)),2) -> 0 | K31: =ROUND(SUM(K6:INDEX(K:K,ROW()-1)),2) -> 0
A32: =ROW()-ROW(A$6) -> 26 | B32: 包装费 | E32: 台 | F32: 1 | G32: 0 | H32: =ROUND(F32*G32,2) -> 0 | J32: =ROUND(H32,2) -> 0
A33: =ROW()-ROW(A$6) -> 27 | B33: 运输费 | E33: 套 | F33: 1 | G33: 0 | H33: =ROUND(F33*G33,2) -> 0 | J33: =ROUND(H33,2) -> 0
A34: =ROW()-ROW(A$6) -> 28 | B34: 运载工具车 | E34: 台 | F34: 1 | G34: 0 | H34: =ROUND(F34*G34,2) -> 0 | J34: =ROUND(H34,2) -> 0
A35: =ROW()-ROW(A$6) -> 29 | B35: 合计(人民币大写) | C35: =TEXT(SUBSTITUTE(IF(H35="","",IF(MOD(H35,1)=0,TEXT(INT(H35),"[DBNum2][$-804]G/通用格式元整"),(TEXT(INT(H35),"[DBNum2][$-804]G/通用格式元")&TEXT((INT(H35*10)-INT(H35)*10),"[DBNum2][$-804]G/通用格式角")&TEXT((INT(H35*100)-INT(H35*10)*10),"[DBNum2][$-804]G/通用格式分")))),"零角","零"),) -> 零元整 | F35: =IF(INDIRECT("'项目信息'!H29")="箱变", 1, "") | G35: =ROUND(SUM(H31:H34),2) -> 0 | H35: =ROUND(IF(F35="",1,F35)*G35,2) -> 0 | J35: =ROUND(IF(F35="",1,F35)*SUM(J31:J34),2) -> 0 | K35: =ROUND(IF(F35="",1,F35)*SUM(K31:K34),2) -> 0 | L35: =IF(H35=0,0,K35/H35) -> 0
A36: 说明
B40: {=CONCATENATE("报价人：", INDIRECT("项目信息!$B$8"))} -> 报价人：李四 | H40: {=INDIRECT("项目信息!$B$9")} -> 0
A41: =T(INDIRECT("项目信息!B22")) -> 扬州华科
A42: =T(INDIRECT("项目信息!B23"))
A43: 成套产品报价明细表
A44: 柜号： | B44: 箱柜1 | C44: 型号: | F44: 名称: | J44: 箱柜尺寸: | L44: 类别:
A45: 序号 | B45: 元件名称 | C45: 型号规格 | D45: 生产厂家 | E45: 单位 | F45: 数量 | G45: 单 价 | H45: 总 价 | I45: 备注 | J45: 成本单价 | K45: 成本总价 | L45: 报出 系数 | M45: 表价 | N45: 折扣 系数 | O45: 取费 系数 | P45: 成套费 | Q45: 类别 | R45: 加工费 | S45: 人工 | T45: 辅料 | W45: 电流 | X45: 极数 | Y45: 脱扣 | Z45: 附件 | AA45: 参数1 | AB45: 参数2
A46: =ROW()-ROW(A$45) -> 1 | E46: =IF(AND(B46="",C46=""),"","只") | F46: =IF(AND(B46="",C46=""),"",1) | G46: =IF(AND(B46="",C46=""),"",ROUND(M46*L46*N46,2)) | H46: =IF(AND(B46="",C46=""),"",ROUND(F46*G46,2)) | J46: =IF(AND(B46="",C46=""),"",ROUND(M46*N46,2)) | K46: =IF(AND(B46="",C46=""),"",ROUND(J46*F46,2)) | L46: =IF(AND(B46="",C46=""),"",1) | N46: =IF(AND(B46="",C46=""),"",1) | Q46: =IF(AND(B46="",C46=""),"","元件")
A47: =ROW()-ROW(A$45) -> 2 | E47: =IF(AND(B47="",C47=""),"","只") | F47: =IF(AND(B47="",C47=""),"",1) | G47: =IF(AND(B47="",C47=""),"",ROUND(M47*L47*N47,2)) | H47: =IF(AND(B47="",C47=""),"",ROUND(F47*G47,2)) | J47: =IF(AND(B47="",C47=""),"",ROUND(M47*N47,2)) | K47: =IF(AND(B47="",C47=""),"",ROUND(J47*F47,2)) | L47: =IF(AND(B47="",C47=""),"",1) | N47: =IF(AND(B47="",C47=""),"",1) | Q47: =IF(AND(B47="",C47=""),"","元件")
A48: =ROW()-ROW(A$45) -> 3 | E48: =IF(AND(B48="",C48=""),"","只") | F48: =IF(AND(B48="",C48=""),"",1) | G48: =IF(AND(B48="",C48=""),"",ROUND(M48*L48*N48,2)) | H48: =IF(AND(B48="",C48=""),"",ROUND(F48*G48,2)) | J48: =IF(AND(B48="",C48=""),"",ROUND(M48*N48,2)) | K48: =IF(AND(B48="",C48=""),"",ROUND(J48*F48,2)) | L48: =IF(AND(B48="",C48=""),"",1) | N48: =IF(AND(B48="",C48=""),"",1) | Q48: =IF(AND(B48="",C48=""),"","元件")
A49: =ROW()-ROW(A$45) -> 4 | E49: =IF(AND(B49="",C49=""),"","只") | F49: =IF(AND(B49="",C49=""),"",1) | G49: =IF(AND(B49="",C49=""),"",ROUND(M49*L49*N49,2)) | H49: =IF(AND(B49="",C49=""),"",ROUND(F49*G49,2)) | J49: =IF(AND(B49="",C49=""),"",ROUND(M49*N49,2)) | K49: =IF(AND(B49="",C49=""),"",ROUND(J49*F49,2)) | L49: =IF(AND(B49="",C49=""),"",1) | N49: =IF(AND(B49="",C49=""),"",1) | Q49: =IF(AND(B49="",C49=""),"","元件")
A50: =ROW()-ROW(A$45) -> 5 | E50: =IF(AND(B50="",C50=""),"","只") | F50: =IF(AND(B50="",C50=""),"",1) | G50: =IF(AND(B50="",C50=""),"",ROUND(M50*L50*N50,2)) | H50: =IF(AND(B50="",C50=""),"",ROUND(F50*G50,2)) | J50: =IF(AND(B50="",C50=""),"",ROUND(M50*N50,2)) | K50: =IF(AND(B50="",C50=""),"",ROUND(J50*F50,2)) | L50: =IF(AND(B50="",C50=""),"",1) | N50: =IF(AND(B50="",C50=""),"",1) | Q50: =IF(AND(B50="",C50=""),"","元件")
A51: =ROW()-ROW(A$45) -> 6 | E51: =IF(AND(B51="",C51=""),"","只") | F51: =IF(AND(B51="",C51=""),"",1) | G51: =IF(AND(B51="",C51=""),"",ROUND(M51*L51*N51,2)) | H51: =IF(AND(B51="",C51=""),"",ROUND(F51*G51,2)) | J51: =IF(AND(B51="",C51=""),"",ROUND(M51*N51,2)) | K51: =IF(AND(B51="",C51=""),"",ROUND(J51*F51,2)) | L51: =IF(AND(B51="",C51=""),"",1) | N51: =IF(AND(B51="",C51=""),"",1) | Q51: =IF(AND(B51="",C51=""),"","元件")
A52: =ROW()-ROW(A$45) -> 7 | E52: =IF(AND(B52="",C52=""),"","只") | F52: =IF(AND(B52="",C52=""),"",1) | G52: =IF(AND(B52="",C52=""),"",ROUND(M52*L52*N52,2)) | H52: =IF(AND(B52="",C52=""),"",ROUND(F52*G52,2)) | J52: =IF(AND(B52="",C52=""),"",ROUND(M52*N52,2)) | K52: =IF(AND(B52="",C52=""),"",ROUND(J52*F52,2)) | L52: =IF(AND(B52="",C52=""),"",1) | N52: =IF(AND(B52="",C52=""),"",1) | Q52: =IF(AND(B52="",C52=""),"","元件")
A53: =ROW()-ROW(A$45) -> 8 | E53: =IF(AND(B53="",C53=""),"","只") | F53: =IF(AND(B53="",C53=""),"",1) | G53: =IF(AND(B53="",C53=""),"",ROUND(M53*L53*N53,2)) | H53: =IF(AND(B53="",C53=""),"",ROUND(F53*G53,2)) | J53: =IF(AND(B53="",C53=""),"",ROUND(M53*N53,2)) | K53: =IF(AND(B53="",C53=""),"",ROUND(J53*F53,2)) | L53: =IF(AND(B53="",C53=""),"",1) | N53: =IF(AND(B53="",C53=""),"",1) | Q53: =IF(AND(B53="",C53=""),"","元件")
A54: =ROW()-ROW(A$45) -> 9 | E54: =IF(AND(B54="",C54=""),"","只") | F54: =IF(AND(B54="",C54=""),"",1) | G54: =IF(AND(B54="",C54=""),"",ROUND(M54*L54*N54,2)) | H54: =IF(AND(B54="",C54=""),"",ROUND(F54*G54,2)) | J54: =IF(AND(B54="",C54=""),"",ROUND(M54*N54,2)) | K54: =IF(AND(B54="",C54=""),"",ROUND(J54*F54,2)) | L54: =IF(AND(B54="",C54=""),"",1) | N54: =IF(AND(B54="",C54=""),"",1) | Q54: =IF(AND(B54="",C54=""),"","元件")
A55: =ROW()-ROW(A$45) -> 10 | E55: =IF(AND(B55="",C55=""),"","只") | F55: =IF(AND(B55="",C55=""),"",1) | G55: =IF(AND(B55="",C55=""),"",ROUND(M55*L55*N55,2)) | H55: =IF(AND(B55="",C55=""),"",ROUND(F55*G55,2)) | J55: =IF(AND(B55="",C55=""),"",ROUND(M55*N55,2)) | K55: =IF(AND(B55="",C55=""),"",ROUND(J55*F55,2)) | L55: =IF(AND(B55="",C55=""),"",1) | N55: =IF(AND(B55="",C55=""),"",1) | Q55: =IF(AND(B55="",C55=""),"","元件")
A56: =ROW()-ROW(A$45) -> 11 | E56: =IF(AND(B56="",C56=""),"","只") | F56: =IF(AND(B56="",C56=""),"",1) | G56: =IF(AND(B56="",C56=""),"",ROUND(M56*L56*N56,2)) | H56: =IF(AND(B56="",C56=""),"",ROUND(F56*G56,2)) | J56: =IF(AND(B56="",C56=""),"",ROUND(M56*N56,2)) | K56: =IF(AND(B56="",C56=""),"",ROUND(J56*F56,2)) | L56: =IF(AND(B56="",C56=""),"",1) | N56: =IF(AND(B56="",C56=""),"",1) | Q56: =IF(AND(B56="",C56=""),"","元件")
A57: =ROW()-ROW(A$45) -> 12 | E57: =IF(AND(B57="",C57=""),"","只") | F57: =IF(AND(B57="",C57=""),"",1) | G57: =IF(AND(B57="",C57=""),"",ROUND(M57*L57*N57,2)) | H57: =IF(AND(B57="",C57=""),"",ROUND(F57*G57,2)) | J57: =IF(AND(B57="",C57=""),"",ROUND(M57*N57,2)) | K57: =IF(AND(B57="",C57=""),"",ROUND(J57*F57,2)) | L57: =IF(AND(B57="",C57=""),"",1) | N57: =IF(AND(B57="",C57=""),"",1) | Q57: =IF(AND(B57="",C57=""),"","元件")
... A63: =ROW()-ROW(A$45) -> 18 | E63: =IF(AND(B63="",C63=""),"","只") | F63: =IF(AND(B63="",C63=""),"",1) | G63: =IF(AND(B63="",C63=""),"",ROUND(M63*L63*N63,2)) | H63: =IF(AND(B63="",C63=""),"",ROUND(F63*G63,2)) | J63: =IF(AND(B63="",C63=""),"",ROUND(M63*N63,2)) | K63: =IF(AND(B63="",C63=""),"",ROUND(J63*F63,2)) | L63: =IF(AND(B63="",C63=""),"",1) | N63: =IF(AND(B63="",C63=""),"",1) | Q63: =IF(AND(B63="",C63=""),"","元件")
A64: [1] | B64: 辅材 | E64: 台 | F64: 1 | G64: =IF(AND(B64="",C64=""),"",ROUND(M64*L64,2)) -> 0 | H64: =ROUND(F64*G64, 2) -> 0 | K64: =ROUND(F64*M64, 2) -> 0 | L64: 1 | Q64: 辅材
A65: [2] | B65: 箱体 | E65: 台 | F65: 1 | G65: =IF(AND(B65="",C65=""),"",ROUND(M65*L65,2)) -> 0 | H65: =ROUND(F65*G65, 2) -> 0 | K65: =ROUND(F65*M65, 2) -> 0 | L65: 1 | Q65: 箱体
A66: [3] | B66: 小计 | H66: =ROUND(SUM(H45:INDEX(H:H,ROW()-1)),2) -> 0 | K66: =ROUND(SUM(K45:INDEX(K:K,ROW()-1)),2) -> 0 | S66: =ROUND(SUMPRODUCT(F45:INDEX(F:F,ROW()-1),S45:INDEX(S:S,ROW()-1)),2) -> 0 | T66: =ROUND(SUMPRODUCT(F45:INDEX(F:F,ROW()-1),T45:INDEX(T:T,ROW()-1)),2) -> 0
A67: [4] | B67: 人工费 | E67: 台 | F67: 1 | G67: =IF(AND(B67="",C67=""),"",ROUND(M67*L67,2)) -> 0 | H67: =ROUND(F67*G67, 2) -> 0 | K67: =ROUND(F67*J67, 2) -> 0 | L67: 1.18 | M67: =ROUND(SUMPRODUCT(F46:INDEX(F:F,ROW()-1),S46:INDEX(S:S,ROW()-1)),2) -> 0 | Q67: 人工费
A68: [5] | B68: 综合成套费 | H68: =ROUND((H66+H67)*0.1, 2) -> 0 | Q68: 费用
A69: [6] | B69: 税金 | H69: =ROUND(SUM(H66:H68)*0.13, 2) -> 0 | Q69: 费用
A70: [7] | B70: 单台合计 | H70: =ROUND(SUM(H66:H69), 2) -> 0 | K70: =ROUND(SUM(K66:K69), 2) -> 0
A71: 总计 | E71: 台 | F71: =F7 -> 1 | G71: =ROUND(H70, 2) -> 0 | H71: =ROUND(F71*G71, 2) -> 0 | K71: =ROUND(K70*F71, 2) -> 0
B74: {=CONCATENATE("报价人：", INDIRECT("项目信息!$B$8"))} -> 报价人：李四 | H74: {=INDIRECT("项目信息!$B$9")} -> 0

Sheet 采购清单
A1: [公司名称]
A2: 采 购 清 单
A4: 项目名称：[项目名称]
A6: 序号 | B6: 名称 | C6: 型号规格 | D6: 单位 | E6: 单数 | F6: 要求到货时间 | G6: 合同到货时间 | H6: 实际到货时间 | I6: 备注
B7: [元器件名称] | C7: [型号] | D7: [单位] | E7: [数量] | I7: [品牌]

Sheet 人工清单
A1: 附件1：
A2: [公司名称]
A3: 人 工 清 单
A4: 队组：金旭彬/陈谦胜
A5: 项目名称：[[项目名称]]
A6: 序号 | B6: 名称 | C6: 型 号 | D6: 数量 | E6: 单位 | F6: 单价（元） | G6: 金额（元） | H6: 备注
A7: [箱柜序号] | B7: [箱柜名称] | C7: [柜号] | D7: [数量] | E7: 台 | F7: [人工费]
B13: 合计 | D13: =SUM(D6:D12) -> 0 | E13: 台 | G13: =ROUND(SUM(G6:G12),0) -> 0
A14: ="合计RMB："& TEXT(SUBSTITUTE(IF(G13="","",IF(MOD(G13,1)=0,TEXT(INT(G13),"[DBNum2][$-804]G/通用格式元整"),(TEXT(INT(G13),"[DBNum2][$-804]G/通用格式元")&TEXT((INT(G13*10)-INT(G13)*10),"[DBNum2][$-804]G/通用格式角")&TEXT((INT(G13*100)-INT(G13*10)*10),"[DBNum2][$-804]G/通用格式分")))),"零角","零"),) -> 合计RMB：零元整
A16: 审核: 编制: 日期: 年 月 日

Sheet 成品交接单
A1: 附件1：
A2: [公司名称]
A3: 成品交接单
A4: 单位名称：扬建集团机电分公司
A5: =[1]报价明细!A4 -> 项目名称：GZ460
A6: 序号 | B6: 名称 | C6: 型 号 | D6: 数量 | E6: 单位 | F6: 箱柜型号 | G6: 电流 | H6: 防护等级 | I6: 备注
A7: [箱柜序号] | B7: 配电箱 | C7: [柜号] | D7: [数量] | E7: 台 | F7: [箱柜型号] | G7: [首行电流] | I7: [分类名称]
B13: 合计 | D13: =SUM(D6:D12) -> 0 | E13: 台 | H13: =ROUND(SUM(H6:H12),0) -> 0
A15: 队组： 调试人： 产成品入库： 日期： 年 月 日
